petrocalc/__init__.py
petrocalc/completion.py
petrocalc/drilling.py
petrocalc/economics.py
petrocalc/enhanced_recovery.py
petrocalc/facilities.py
petrocalc/flow.py
petrocalc/fluids.py
petrocalc/gas_reservoir.py
petrocalc/geomechanics.py
petrocalc/laboratory.py
petrocalc/petrophysics.py
petrocalc/pressure.py
petrocalc/production.py
petrocalc/reservoir.py
petrocalc/rock_properties.py
petrocalc/thermodynamics.py
petrocalc/well_testing.py
petrocalc-1.2.1.dist-info/METADATA
petrocalc-1.2.1.dist-info/WHEEL
petrocalc-1.2.1.dist-info/licenses/LICENSE
petrocalc-1.2.1.dist-info/RECORD
