Metadata-Version: 2.4
Name: petrocalc
Version: 1.2.1
Summary: A comprehensive Python library for petroleum engineering calculations
License: MIT
License-File: LICENSE
Keywords: petroleum engineering,oil and gas,drilling,reservoir engineering,production engineering,fluid properties,economics,pvt,well testing
Author: Muhammad Farzad Ali
Author-email: muhammad.farzad.ali@gmail.com
Requires-Python: >=3.10
Classifier: Development Status :: 4 - Beta
Classifier: Intended Audience :: Science/Research
Classifier: Intended Audience :: Developers
Classifier: License :: OSI Approved :: MIT License
Classifier: Operating System :: OS Independent
Classifier: Programming Language :: Python :: 3
Classifier: Programming Language :: Python :: 3.10
Classifier: Programming Language :: Python :: 3.11
Classifier: Programming Language :: Python :: 3.12
Classifier: Topic :: Scientific/Engineering
Classifier: Topic :: Scientific/Engineering :: Physics
Classifier: Topic :: Software Development :: Libraries :: Python Modules
Provides-Extra: dev
Provides-Extra: docs
Requires-Dist: black (>=23.0) ; extra == "dev"
Requires-Dist: flake8 (>=6.0) ; extra == "dev"
Requires-Dist: mypy (>=1.0) ; extra == "dev"
Requires-Dist: pytest (>=7.0) ; extra == "dev"
Requires-Dist: pytest-cov (>=4.0) ; extra == "dev"
Requires-Dist: sphinx (>=6.0) ; extra == "docs"
Requires-Dist: sphinx-rtd-theme (>=1.0) ; extra == "docs"
Project-URL: Bug Tracker, https://github.com/your-username/petrocalc/issues
Project-URL: Documentation, https://petrocalc.readthedocs.io/
Project-URL: Homepage, https://github.com/your-username/petrocalc
Project-URL: Repository, https://github.com/your-username/petrocalc.git
